{
    "alias": null,
    "articles": [
        {
            "articleVersion": "1.0",
            "cid": "JORFARTI000031027090",
            "comporteLiens": false,
            "conditionDiffere": null,
            "content": "<p>Les dispositions de l'annexe I sont applicables aux installations déclarées à compter du 1er janvier 2016 .</p><p>Les dispositions de l'annexe I sont applicables aux installations existantes, déclarées avant le 1er janvier 2016, dans les conditions précisées en annexe III. Les prescriptions auxquelles les installations existantes sont déjà soumises demeurent applicables jusqu'à l'entrée en vigueur de ces dispositions.</p><p>Les dispositions de l'annexe I sont également applicables aux installations classées soumises à déclaration incluses dans un établissement qui comporte au moins une installation soumise au régime de l'autorisation dès lors que ces installations ne sont pas régies par l'arrêté préfectoral d'autorisation.<br/></p><p>A abrogé les dispositions suivantes : </p><blockquote>- <a href='/affichTexte.do?cidTexte=JORFTEXT000000183179&dateTexte=&categorieLien=id' title='Arrêté du 30 juin 1997 (VT)'>Arrêté du 30 juin 1997</a><blockquote><a href='/affichTexteArticle.do?cidTexte=JORFTEXT000000183179&idArticle=LEGIARTI000006870261&dateTexte=&categorieLien=id' title='Arrêté du 30 juin 1997 - art. 1 (VT)'>Art. 1</a>, <a href='/affichTexteArticle.do?cidTexte=JORFTEXT000000183179&idArticle=LEGIARTI000006870262&dateTexte=&categorieLien=id' title='Arrêté du 30 juin 1997 - art. 2 (VT)'>Art. 2</a>, <a href='/affichTexteArticle.do?cidTexte=JORFTEXT000000183179&idArticle=LEGIARTI000006870263&dateTexte=&categorieLien=id' title='Arrêté du 30 juin 1997 - art. 3 (VT)'>Art. 3</a>, <a href='/affichTexteArticle.do?cidTexte=JORFTEXT000000183179&idArticle=LEGIARTI000006870260&dateTexte=&categorieLien=id' title='Arrêté du 30 juin 1997 - art. 4 (VT)'>Art. 4</a>, <a href='/affichTexte.do?cidTexte=JORFTEXT000000183179&idSectionTA=LEGISCTA000006110908&dateTexte=&categorieLien=id' title='Arrêté du 30 juin 1997 -  Annexes (VT)'>Sct. Annexes</a>, <a href='/affichTexte.do?cidTexte=JORFTEXT000000183179&idSectionTA=LEGISCTA000006130718&dateTexte=&categorieLien=id' title='Arrêté du 30 juin 1997 -  I. Dispositions générales. (VT)'>Sct. I. Dispositions générales.</a>, <a href='/affichTexteArticle.do?cidTexte=JORFTEXT000000183179&idArticle=LEGIARTI000006870264&dateTexte=&categorieLien=id' title='Arrêté du 30 juin 1997 - art. Annexe I (VT)'>Art. Annexe I</a>, <a href='/affichTexte.do?cidTexte=JORFTEXT000000183179&idSectionTA=LEGISCTA000006130719&dateTexte=&categorieLien=id' title='Arrêté du 30 juin 1997 -  II. Implantation, aménagement. (VT)'>Sct. II. Implantation, aménagement.</a>, <a href='/affichTexteArticle.do?cidTexte=JORFTEXT000000183179&idArticle=LEGIARTI000006870265&dateTexte=&categorieLien=id' title='Arrêté du 30 juin 1997 - art. Annexe I (VT)'>Art. Annexe I</a>, <a href='/affichTexte.do?cidTexte=JORFTEXT000000183179&idSectionTA=LEGISCTA000006130720&dateTexte=&categorieLien=id' title='Arrêté du 30 juin 1997 -  III. Exploitation, entretien. (VT)'>Sct. III. Exploitation, entretien.</a>, <a href='/affichTexteArticle.do?cidTexte=JORFTEXT000000183179&idArticle=LEGIARTI000006870266&dateTexte=&categorieLien=id' title='Arrêté du 30 juin 1997 - art. Annexe I (VT)'>Art. Annexe I</a>, <a href='/affichTexte.do?cidTexte=JORFTEXT000000183179&idSectionTA=LEGISCTA000006130721&dateTexte=&categorieLien=id' title='Arrêté du 30 juin 1997 -  IV. Risques. (VT)'>Sct. IV. Risques.</a>, <a href='/affichTexteArticle.do?cidTexte=JORFTEXT000000183179&idArticle=LEGIARTI000006870267&dateTexte=&categorieLien=id' title='Arrêté du 30 juin 1997 - art. Annexe I (VT)'>Art. Annexe I</a>, <a href='/affichTexte.do?cidTexte=JORFTEXT000000183179&idSectionTA=LEGISCTA000006130722&dateTexte=&categorieLien=id' title='Arrêté du 30 juin 1997 -  V. Eau. (VT)'>Sct. V. Eau.</a>, <a href='/affichTexteArticle.do?cidTexte=JORFTEXT000000183179&idArticle=LEGIARTI000006870268&dateTexte=&categorieLien=id' title='Arrêté du 30 juin 1997 - art. Annexe I (VT)'>Art. Annexe I</a>, <a href='/affichTexte.do?cidTexte=JORFTEXT000000183179&idSectionTA=LEGISCTA000006130723&dateTexte=&categorieLien=id' title='Arrêté du 30 juin 1997 -  VI. Air, odeurs. (VT)'>Sct. VI. Air, odeurs.</a>, <a href='/affichTexteArticle.do?cidTexte=JORFTEXT000000183179&idArticle=LEGIARTI000006870269&dateTexte=&categorieLien=id' title='Arrêté du 30 juin 1997 - art. Annexe I (VT)'>Art. Annexe I</a>, <a href='/affichTexte.do?cidTexte=JORFTEXT000000183179&idSectionTA=LEGISCTA000006130724&dateTexte=&categorieLien=id' title='Arrêté du 30 juin 1997 -  VII. Déchets. (VT)'>Sct. VII. Déchets.</a>, <a href='/affichTexteArticle.do?cidTexte=JORFTEXT000000183179&idArticle=LEGIARTI000006870270&dateTexte=&categorieLien=id' title='Arrêté du 30 juin 1997 - art. Annexe I (VT)'>Art. Annexe I</a>, <a href='/affichTexte.do?cidTexte=JORFTEXT000000183179&idSectionTA=LEGISCTA000006130725&dateTexte=&categorieLien=id' title='Arrêté du 30 juin 1997 -  VIII. Bruit et vibrations. (VT)'>Sct. VIII. Bruit et vibrations.</a>, <a href='/affichTexteArticle.do?cidTexte=JORFTEXT000000183179&idArticle=LEGIARTI000006870273&dateTexte=&categorieLien=id' title='Arrêté du 30 juin 1997 - art. Annexe I (VT)'>Art. Annexe I</a>, <a href='/affichTexte.do?cidTexte=JORFTEXT000000183179&idSectionTA=LEGISCTA000006130726&dateTexte=&categorieLien=id' title='Arrêté du 30 juin 1997 -  IX. Remise en état en fin d'exploitation. (VT)'>Sct. IX. Remise en état en fin d'exploitation.</a>, <a href='/affichTexteArticle.do?cidTexte=JORFTEXT000000183179&idArticle=LEGIARTI000006870274&dateTexte=&categorieLien=id' title='Arrêté du 30 juin 1997 - art. Annexe I (VT)'>Art. Annexe I</a>, <a href='/affichTexte.do?cidTexte=JORFTEXT000000183179&idSectionTA=LEGISCTA000006130727&dateTexte=&categorieLien=id' title='Arrêté du 30 juin 1997 -  Dispositions applicables aux installations exis... (VT)'>Sct. Dispositions applicables aux installations existantes.</a>, <a href='/affichTexteArticle.do?cidTexte=JORFTEXT000000183179&idArticle=LEGIARTI000006870275&dateTexte=&categorieLien=id' title='Arrêté du 30 juin 1997 - art. Annexe II (VT)'>Art. Annexe II</a></blockquote></blockquote>",
            "dereferenced": false,
            "etat": "VIGUEUR",
            "executionTime": 0,
            "historique": null,
            "id": "LEGIARTI000031042953",
            "intOrdre": 1048574,
            "lstLienCitation": [],
            "lstLienModification": [
                {
                    "articleId": "LEGITEXT000005624013",
                    "articleNum": "",
                    "dateDebutCible": "1997-07-30",
                    "datePubliTexte": "1997-07-30",
                    "dateSignaTexte": "1997-06-30",
                    "linkOrientation": "source",
                    "linkType": "ABROGE",
                    "natureText": "ARRETE",
                    "textCid": "JORFTEXT000000183179",
                    "textTitle": "Arrêté du 30 juin 1997 (VT)"
                },
                {
                    "articleId": "LEGISCTA000006110908",
                    "articleNum": "",
                    "dateDebutCible": "1997-08-25",
                    "datePubliTexte": "1997-07-30",
                    "dateSignaTexte": "1997-06-30",
                    "linkOrientation": "source",
                    "linkType": "ABROGE",
                    "natureText": "ARRETE",
                    "textCid": "JORFTEXT000000183179",
                    "textTitle": "Arrêté du 30 juin 1997 -  Annexes (VT)"
                },
                {
                    "articleId": "LEGISCTA000006130727",
                    "articleNum": "",
                    "dateDebutCible": "1997-08-25",
                    "datePubliTexte": "1997-07-30",
                    "dateSignaTexte": "1997-06-30",
                    "linkOrientation": "source",
                    "linkType": "ABROGE",
                    "natureText": "ARRETE",
                    "textCid": "JORFTEXT000000183179",
                    "textTitle": "Arrêté du 30 juin 1997 -  Dispositions applicables aux installations exis... (VT)"
                },
                {
                    "articleId": "LEGISCTA000006130718",
                    "articleNum": "",
                    "dateDebutCible": "1997-08-25",
                    "datePubliTexte": "1997-07-30",
                    "dateSignaTexte": "1997-06-30",
                    "linkOrientation": "source",
                    "linkType": "ABROGE",
                    "natureText": "ARRETE",
                    "textCid": "JORFTEXT000000183179",
                    "textTitle": "Arrêté du 30 juin 1997 -  I. Dispositions générales. (VT)"
                },
                {
                    "articleId": "LEGISCTA000006130719",
                    "articleNum": "",
                    "dateDebutCible": "1997-08-25",
                    "datePubliTexte": "1997-07-30",
                    "dateSignaTexte": "1997-06-30",
                    "linkOrientation": "source",
                    "linkType": "ABROGE",
                    "natureText": "ARRETE",
                    "textCid": "JORFTEXT000000183179",
                    "textTitle": "Arrêté du 30 juin 1997 -  II. Implantation, aménagement. (VT)"
                },
                {
                    "articleId": "LEGISCTA000006130720",
                    "articleNum": "",
                    "dateDebutCible": "1997-08-25",
                    "datePubliTexte": "1997-07-30",
                    "dateSignaTexte": "1997-06-30",
                    "linkOrientation": "source",
                    "linkType": "ABROGE",
                    "natureText": "ARRETE",
                    "textCid": "JORFTEXT000000183179",
                    "textTitle": "Arrêté du 30 juin 1997 -  III. Exploitation, entretien. (VT)"
                },
                {
                    "articleId": "LEGISCTA000006130721",
                    "articleNum": "",
                    "dateDebutCible": "1997-08-25",
                    "datePubliTexte": "1997-07-30",
                    "dateSignaTexte": "1997-06-30",
                    "linkOrientation": "source",
                    "linkType": "ABROGE",
                    "natureText": "ARRETE",
                    "textCid": "JORFTEXT000000183179",
                    "textTitle": "Arrêté du 30 juin 1997 -  IV. Risques. (VT)"
                },
                {
                    "articleId": "LEGISCTA000006130726",
                    "articleNum": "",
                    "dateDebutCible": "1997-08-25",
                    "datePubliTexte": "1997-07-30",
                    "dateSignaTexte": "1997-06-30",
                    "linkOrientation": "source",
                    "linkType": "ABROGE",
                    "natureText": "ARRETE",
                    "textCid": "JORFTEXT000000183179",
                    "textTitle": "Arrêté du 30 juin 1997 -  IX. Remise en état en fin d'exploitation. (VT)"
                },
                {
                    "articleId": "LEGISCTA000006130722",
                    "articleNum": "",
                    "dateDebutCible": "1997-08-25",
                    "datePubliTexte": "1997-07-30",
                    "dateSignaTexte": "1997-06-30",
                    "linkOrientation": "source",
                    "linkType": "ABROGE",
                    "natureText": "ARRETE",
                    "textCid": "JORFTEXT000000183179",
                    "textTitle": "Arrêté du 30 juin 1997 -  V. Eau. (VT)"
                },
                {
                    "articleId": "LEGISCTA000006130723",
                    "articleNum": "",
                    "dateDebutCible": "1997-08-25",
                    "datePubliTexte": "1997-07-30",
                    "dateSignaTexte": "1997-06-30",
                    "linkOrientation": "source",
                    "linkType": "ABROGE",
                    "natureText": "ARRETE",
                    "textCid": "JORFTEXT000000183179",
                    "textTitle": "Arrêté du 30 juin 1997 -  VI. Air, odeurs. (VT)"
                },
                {
                    "articleId": "LEGISCTA000006130724",
                    "articleNum": "",
                    "dateDebutCible": "1997-08-25",
                    "datePubliTexte": "1997-07-30",
                    "dateSignaTexte": "1997-06-30",
                    "linkOrientation": "source",
                    "linkType": "ABROGE",
                    "natureText": "ARRETE",
                    "textCid": "JORFTEXT000000183179",
                    "textTitle": "Arrêté du 30 juin 1997 -  VII. Déchets. (VT)"
                },
                {
                    "articleId": "LEGISCTA000006130725",
                    "articleNum": "",
                    "dateDebutCible": "1997-08-25",
                    "datePubliTexte": "1997-07-30",
                    "dateSignaTexte": "1997-06-30",
                    "linkOrientation": "source",
                    "linkType": "ABROGE",
                    "natureText": "ARRETE",
                    "textCid": "JORFTEXT000000183179",
                    "textTitle": "Arrêté du 30 juin 1997 -  VIII. Bruit et vibrations. (VT)"
                },
                {
                    "articleId": "LEGIARTI000006870261",
                    "articleNum": "1",
                    "dateDebutCible": "1997-07-30",
                    "datePubliTexte": "1997-07-30",
                    "dateSignaTexte": "1997-06-30",
                    "linkOrientation": "source",
                    "linkType": "ABROGE",
                    "natureText": "ARRETE",
                    "textCid": "JORFTEXT000000183179",
                    "textTitle": "Arrêté du 30 juin 1997 - art. 1 (VT)"
                },
                {
                    "articleId": "LEGIARTI000006870262",
                    "articleNum": "2",
                    "dateDebutCible": "1997-07-30",
                    "datePubliTexte": "1997-07-30",
                    "dateSignaTexte": "1997-06-30",
                    "linkOrientation": "source",
                    "linkType": "ABROGE",
                    "natureText": "ARRETE",
                    "textCid": "JORFTEXT000000183179",
                    "textTitle": "Arrêté du 30 juin 1997 - art. 2 (VT)"
                },
                {
                    "articleId": "LEGIARTI000006870263",
                    "articleNum": "3",
                    "dateDebutCible": "1997-07-30",
                    "datePubliTexte": "1997-07-30",
                    "dateSignaTexte": "1997-06-30",
                    "linkOrientation": "source",
                    "linkType": "ABROGE",
                    "natureText": "ARRETE",
                    "textCid": "JORFTEXT000000183179",
                    "textTitle": "Arrêté du 30 juin 1997 - art. 3 (VT)"
                },
                {
                    "articleId": "LEGIARTI000006870260",
                    "articleNum": "4",
                    "dateDebutCible": "1997-07-30",
                    "datePubliTexte": "1997-07-30",
                    "dateSignaTexte": "1997-06-30",
                    "linkOrientation": "source",
                    "linkType": "ABROGE",
                    "natureText": "ARRETE",
                    "textCid": "JORFTEXT000000183179",
                    "textTitle": "Arrêté du 30 juin 1997 - art. 4 (VT)"
                },
                {
                    "articleId": "LEGIARTI000006870274",
                    "articleNum": "Annexe I",
                    "dateDebutCible": "1997-08-25",
                    "datePubliTexte": "1997-07-30",
                    "dateSignaTexte": "1997-06-30",
                    "linkOrientation": "source",
                    "linkType": "ABROGE",
                    "natureText": "ARRETE",
                    "textCid": "JORFTEXT000000183179",
                    "textTitle": "Arrêté du 30 juin 1997 - art. Annexe I (VT)"
                },
                {
                    "articleId": "LEGIARTI000006870273",
                    "articleNum": "Annexe I",
                    "dateDebutCible": "1997-08-25",
                    "datePubliTexte": "1997-07-30",
                    "dateSignaTexte": "1997-06-30",
                    "linkOrientation": "source",
                    "linkType": "ABROGE",
                    "natureText": "ARRETE",
                    "textCid": "JORFTEXT000000183179",
                    "textTitle": "Arrêté du 30 juin 1997 - art. Annexe I (VT)"
                },
                {
                    "articleId": "LEGIARTI000006870270",
                    "articleNum": "Annexe I",
                    "dateDebutCible": "1997-08-25",
                    "datePubliTexte": "1997-07-30",
                    "dateSignaTexte": "1997-06-30",
                    "linkOrientation": "source",
                    "linkType": "ABROGE",
                    "natureText": "ARRETE",
                    "textCid": "JORFTEXT000000183179",
                    "textTitle": "Arrêté du 30 juin 1997 - art. Annexe I (VT)"
                },
                {
                    "articleId": "LEGIARTI000006870269",
                    "articleNum": "Annexe I",
                    "dateDebutCible": "1997-08-25",
                    "datePubliTexte": "1997-07-30",
                    "dateSignaTexte": "1997-06-30",
                    "linkOrientation": "source",
                    "linkType": "ABROGE",
                    "natureText": "ARRETE",
                    "textCid": "JORFTEXT000000183179",
                    "textTitle": "Arrêté du 30 juin 1997 - art. Annexe I (VT)"
                },
                {
                    "articleId": "LEGIARTI000006870268",
                    "articleNum": "Annexe I",
                    "dateDebutCible": "1997-08-25",
                    "datePubliTexte": "1997-07-30",
                    "dateSignaTexte": "1997-06-30",
                    "linkOrientation": "source",
                    "linkType": "ABROGE",
                    "natureText": "ARRETE",
                    "textCid": "JORFTEXT000000183179",
                    "textTitle": "Arrêté du 30 juin 1997 - art. Annexe I (VT)"
                },
                {
                    "articleId": "LEGIARTI000006870267",
                    "articleNum": "Annexe I",
                    "dateDebutCible": "1997-08-25",
                    "datePubliTexte": "1997-07-30",
                    "dateSignaTexte": "1997-06-30",
                    "linkOrientation": "source",
                    "linkType": "ABROGE",
                    "natureText": "ARRETE",
                    "textCid": "JORFTEXT000000183179",
                    "textTitle": "Arrêté du 30 juin 1997 - art. Annexe I (VT)"
                },
                {
                    "articleId": "LEGIARTI000006870266",
                    "articleNum": "Annexe I",
                    "dateDebutCible": "1997-08-25",
                    "datePubliTexte": "1997-07-30",
                    "dateSignaTexte": "1997-06-30",
                    "linkOrientation": "source",
                    "linkType": "ABROGE",
                    "natureText": "ARRETE",
                    "textCid": "JORFTEXT000000183179",
                    "textTitle": "Arrêté du 30 juin 1997 - art. Annexe I (VT)"
                },
                {
                    "articleId": "LEGIARTI000006870265",
                    "articleNum": "Annexe I",
                    "dateDebutCible": "1997-08-25",
                    "datePubliTexte": "1997-07-30",
                    "dateSignaTexte": "1997-06-30",
                    "linkOrientation": "source",
                    "linkType": "ABROGE",
                    "natureText": "ARRETE",
                    "textCid": "JORFTEXT000000183179",
                    "textTitle": "Arrêté du 30 juin 1997 - art. Annexe I (VT)"
                },
                {
                    "articleId": "LEGIARTI000006870264",
                    "articleNum": "Annexe I",
                    "dateDebutCible": "1997-08-25",
                    "datePubliTexte": "1997-07-30",
                    "dateSignaTexte": "1997-06-30",
                    "linkOrientation": "source",
                    "linkType": "ABROGE",
                    "natureText": "ARRETE",
                    "textCid": "JORFTEXT000000183179",
                    "textTitle": "Arrêté du 30 juin 1997 - art. Annexe I (VT)"
                },
                {
                    "articleId": "LEGIARTI000006870275",
                    "articleNum": "Annexe II",
                    "dateDebutCible": "1997-08-25",
                    "datePubliTexte": "1997-07-30",
                    "dateSignaTexte": "1997-06-30",
                    "linkOrientation": "source",
                    "linkType": "ABROGE",
                    "natureText": "ARRETE",
                    "textCid": "JORFTEXT000000183179",
                    "textTitle": "Arrêté du 30 juin 1997 - art. Annexe II (VT)"
                }
            ],
            "modificatorCid": null,
            "modificatorDate": null,
            "modificatorTitle": null,
            "nota": "",
            "num": "2",
            "renvoi": null,
            "surtitre": null,
            "type": "ENTIEREMENT_MODIF"
        },
        {
            "articleVersion": "1.0",
            "cid": "JORFARTI000031027089",
            "comporteLiens": false,
            "conditionDiffere": null,
            "content": "<p><br/>Les installations classées soumises à déclaration sous la rubrique n° 2561 (production industrielle par trempe, recuit ou revenu de métaux et alliages) sont soumises aux dispositions de l'annexe I (*).<br/>Les présentes dispositions s'appliquent sans préjudice des autres législations ainsi que des schémas, plans et autres documents d'orientation et de planification approuvés.</p>",
            "dereferenced": false,
            "etat": "VIGUEUR",
            "executionTime": 0,
            "historique": null,
            "id": "LEGIARTI000031042951",
            "intOrdre": 524287,
            "lstLienCitation": [],
            "lstLienModification": [],
            "modificatorCid": null,
            "modificatorDate": null,
            "modificatorTitle": null,
            "nota": "<p></p>",
            "num": "1",
            "renvoi": null,
            "surtitre": null,
            "type": "AUTONOME"
        },
        {
            "articleVersion": "1.0",
            "cid": "JORFARTI000031027100",
            "comporteLiens": false,
            "conditionDiffere": null,
            "content": "<p><br/>La directrice générale de la prévention des risques est chargée de l'exécution du présent arrêté, qui sera publié au Journal officiel de la République française.</p>",
            "dereferenced": false,
            "etat": "VIGUEUR",
            "executionTime": 0,
            "historique": null,
            "id": "LEGIARTI000031042959",
            "intOrdre": 2621435,
            "lstLienCitation": [],
            "lstLienModification": [],
            "modificatorCid": null,
            "modificatorDate": null,
            "modificatorTitle": null,
            "nota": "<p></p>",
            "num": "5",
            "renvoi": null,
            "surtitre": null,
            "type": "AUTONOME"
        },
        {
            "articleVersion": "1.0",
            "cid": "JORFARTI000031027098",
            "comporteLiens": false,
            "conditionDiffere": null,
            "content": "<p><br/>Le présent arrêté entre en vigueur le 1er janvier 2016.</p>",
            "dereferenced": false,
            "etat": "VIGUEUR",
            "executionTime": 0,
            "historique": null,
            "id": "LEGIARTI000031042957",
            "intOrdre": 2097148,
            "lstLienCitation": [],
            "lstLienModification": [],
            "modificatorCid": null,
            "modificatorDate": null,
            "modificatorTitle": null,
            "nota": "",
            "num": "4",
            "renvoi": null,
            "surtitre": null,
            "type": "AUTONOME"
        },
        {
            "articleVersion": "1.0",
            "cid": "JORFARTI000031027094",
            "comporteLiens": true,
            "conditionDiffere": null,
            "content": "<p><br/>Le préfet peut, en application de l'<a href='/affichCodeArticle.do?cidTexte=LEGITEXT000006074220&idArticle=LEGIARTI000006834244&dateTexte=&categorieLien=cid'>article L. 512-10 du code de l'environnement</a>, adapter par arrêté préfectoral aux circonstances locales :</p><p><br/>- installation par installation, les prescriptions du présent arrêté dans les conditions prévues à l'<a href='/affichCodeArticle.do?cidTexte=LEGITEXT000006074220&idArticle=LEGIARTI000006838729&dateTexte=&categorieLien=cid'>article R. 512-52 du code de l'environnement</a> ;<br/>- pour l'ensemble des installations du département, les prescriptions des articles de l'annexe I dans les conditions prévues à l'article L. 512-10 du code de l'environnement.</p>",
            "dereferenced": false,
            "etat": "VIGUEUR",
            "executionTime": 0,
            "historique": null,
            "id": "LEGIARTI000031042955",
            "intOrdre": 1572861,
            "lstLienCitation": [],
            "lstLienModification": [],
            "modificatorCid": null,
            "modificatorDate": null,
            "modificatorTitle": null,
            "nota": "<p></p>",
            "num": "3",
            "renvoi": null,
            "surtitre": null,
            "type": "AUTONOME"
        }
    ],
    "cid": "JORFTEXT000031027083",
    "dateDebutVersion": "2016-01-01",
    "dateFinVersion": "2999-01-01",
    "dateParution": 1439596800000,
    "dereferenced": false,
    "dossiersLegislatifs": [],
    "eli": null,
    "etat": null,
    "executionTime": 19,
    "fileName": null,
    "filePath": null,
    "fileSize": null,
    "id": "LEGITEXT000031042947_01-01-2016",
    "idConteneur": null,
    "inap": false,
    "jorfText": "JORF n°0188 du 15 août 2015",
    "jurisDate": "2016-01-01",
    "jurisState": "Vigueur",
    "liens": [],
    "modifDate": "2016-01-01",
    "motsCles": [],
    "nature": null,
    "nor": "DEVP1510050A",
    "nota": "",
    "notice": null,
    "numParution": "0188",
    "observations": null,
    "prepWork": "",
    "rectificatif": null,
    "resume": null,
    "sections": [],
    "signers": "<p align='left'><br clear='none'/>Fait le 27 juillet 2015.</p><p align='left'><br clear='none'/>Pour la ministre et par délégation :<br clear='none'/>La directrice générale de la prévention des risques,<br clear='none'/>P. Blanc</p><font color='808080'><em>\n        (*) L'arrêté et les annexes seront publiés au Bulletin officiel du ministère de l'écologie, du développement durable et de l'énergie.\n      </em></font>",
    "textAbroge": false,
    "textNumber": null,
    "title": "Arrêté du 27 juillet 2015 relatif aux prescriptions générales applicables aux installations classées pour la protection de l'environnement soumises à déclaration sous la rubrique n° 2561",
    "visa": "<p align='left'><br/>La ministre de l'écologie, du développement durable et de l'énergie,<br/>Vu le <a href='/affichCode.do?cidTexte=LEGITEXT000006074220&dateTexte=29990101&categorieLien=cid' title='Code de l'environnement (V)'>code de l'environnement</a>, notamment le titre Ier du livre V ;<br/>Vu le <a href='/affichCode.do?cidTexte=LEGITEXT000006072050&dateTexte=29990101&categorieLien=cid' title='Code du travail (V)'>code du travail</a> ;<br/>Vu l'arrêté du 7 juillet 2009 relatif aux modalités d'analyse dans l'air et dans l'eau dans les ICPE et aux normes de référence ;<br/>Vu l'avis des organisations professionnelles intéressées ;<br/>Vu les observations formulées lors de la consultation publique réalisée du 26 février au 19 mars 2015, en application de l'<a href='/affichCodeArticle.do?cidTexte=LEGITEXT000006074220&idArticle=LEGIARTI000022484420&dateTexte=29990101&categorieLien=cid' title='Code de l'environnement - art. L120-1 (M)'>article L. 120-1 du code de l'environnement</a> ;<br/>Vu l'avis du Conseil supérieur de la prévention des risques technologiques en date du 14 avril 2015,<br/>Arrête :</p>"
}